SutraMarathi/__init__.py
SutraMarathi/__main__.py
SutraMarathi/interpreter.py
sutramarathi-1.0.0.dist-info/licenses/LICENSE
sutramarathi-1.0.0.dist-info/METADATA
sutramarathi-1.0.0.dist-info/WHEEL
sutramarathi-1.0.0.dist-info/entry_points.txt
sutramarathi-1.0.0.dist-info/top_level.txt
sutramarathi-1.0.0.dist-info/RECORD
