Metadata-Version: 2.4
Name: SutraMarathi
Version: 1.0.0
Summary: Marathi-based programming language interpreter
Home-page: https://sutramarathi.in
Author: Kishor Bhagwat
Author-email: Kishor Bhagwat <bhagwatkishor09@gmail.com>
License: MIT
Project-URL: Homepage, https://sutramarathi.in
Project-URL: Repository, https://github.com/YourGitHubUsername/SutraMarathi
Keywords: programming language,interpreter,Marathi,sutramarathi
Classifier: Programming Language :: Python :: 3
Classifier: License :: OSI Approved :: MIT License
Classifier: Operating System :: OS Independent
Classifier: Topic :: Software Development :: Interpreters
Classifier: Natural Language :: Marathi
Requires-Python: >=3.6
License-File: LICENSE
Dynamic: author
Dynamic: home-page
Dynamic: license-file
Dynamic: requires-python
